{"yflhvMFJ//Gncc19l8RWng==":"mbr-1.jpg","T4zkQrDWb0m9qIv27c5rVg==":"mbr-2.jpg","Z0s7uTFMjKcQ7ngLc5lmnA==":"mbr.jpg","wzidloMrha3tuSON+OV1Cw==":"mbr-3.jpg","FhC12xVKkvIETQMVKu9WsA==":"mbr-4.jpg","XLOa+k8BKjlTYw4d/uEulQ==":"mbr-6.jpg","LAL131GPhuSNnoifNS/NrQ==":"mbr.jpeg","n3xLfiICRwBK7qZAxZQ4ig==":"mbr-6.jpeg","61tx7eiw/R1KSuuIhkCgyw==":"mbr-4.jpeg","7BusHJYMZF5vA0Q1cmlFTQ==":"mbr-9.jpeg","YRJAA6ew0xAs6F0Ax5Rfvw==":"mbr-11.jpeg","DUgaHyV9oTcz7ZCUxJbpSQ==":"mbr-2.jpeg","nmaFfquSo95VQKE0s/iKhQ==":"mbr-3.jpeg","fdrkojhpw03cB3GSjvgDuw==":"mbr-12.jpeg","Gjo+fRcaTLdlEzWBcy0xQw==":"mbr-5.jpg","lNz+1WZ+Jsut4WEwqonaVg==":"mbr-7.jpg","r4SJW6vvdWfNTKjQSApHUw==":"mbr-8.jpg","aj6nI9PXScsDr4XezM2cNg==":"mbr-9.jpg","l3O6KHUARGL95+Th0X0BuQ==":"mbr-10.jpg","lK77ih7fT22RGPy5YZlknA==":"mbr-10.jpeg","9MA44v7wAXZf/YRNZxJK9Q==":"mbr-13.jpeg","uUTtwDNVtKLOj7cIFnet6w==":"mbr-14.jpeg","Q6iFla8InJcXTnXwrhQJBw==":"mbr-15.jpeg","r2I82yeII6avCvXJVP6Hhg==":"mbr-16.jpeg","/HVusEn4Av1iT9/R8YDOAA==":"mbr-11.jpg","CRxHHjX0jfgqDfEHqFpEbQ==":"mbr-17.jpeg","nZ522L3IHqZbQdLdB4urcw==":"mbr-18.jpeg","FUFWlmEDrx/Wq7juCg4sdQ==":"mbr-19.jpeg","kgPc6Z3mClKN6Ps+h/pg/Q==":"mbr-20.jpeg","XG+ONbapUJ3IeBazAjBsVg==":"mbr-1920x1280.jpg","otQHY/BsRWwkWGRaX3plXA==":"professional-camera-aperture-2022-09-16-03-14-04-utc-1897x1000.jpg","IEpucveJDT4jVPZ1tPQM3g==":"digital-camera-2021-08-26-16-26-10-utc-800x607.png","HOrE6gx6V7Kaz4Icg60zig==":"screenshot%202023-03-19%20235320-540x526.png","aF4JSaxuDjhj0HPkcOQ1eA==":"screenshot%202023-03-19%20235320-540x526.png","Q/qy6txQlgh0mhCifF7EvA==":"screenshot%202023-03-19%20235320-540x526.png","nAYirViL726muHc9Cme4zQ==":"mbr-1-1920x1280.jpg","byLutvHcmv7CyZ0lFs24Kw==":"mbr-1920x1080.jpg","iagb3V/NsNuqpljAD1ejWw==":"mbr-2-1920x1280.jpg","N58YwMgFoHXfKSOZi4MotQ==":"video-editor-glyph-iconvideo-production-260nw-2068832198-removebg-preview-260x280.png","y7iELK/u4EQ7Ts4/euPw1g==":"%E2%80%94pngtree%E2%80%94digital%20camera%20black%20and%20white-6016380-432x432.png","ZgqAIqV2IjF3UEQTo2yiMg==":"pngtree-film-clapper-icon-simple-vector-png-image_8072225-removebg-preview-432x432.png","DEsigR0z2a0s2zxEmpF9Mw==":"pngtree-cd-disk-icon-vector-png-image_7832545-removebg-preview-432x432.png","5Eok7Xac99wnlvQMPIMYmw==":"pngtree-black-and-white-retro-style-illustration-of-a-movie-director-looking-png-image_8094680-removebg-preview-432x432.png","5ec+/uRYnPQpdZs6H9SuCg==":"pexels-photo-7148443-1256x707.jpg","5JOB9i29UjDDSoDbtS9B3Q==":"pexels-kaw%C3%AA-rodrigues-16025054-1476x2214.jpg","3klRUV44AupexYNUi7dwMA==":"pexels-kaw%C3%AA-rodrigues-16025054-1476x2214.jpeg","RtEaWkWbPbK831ytdfc5eA==":"%E2%80%94pngtree%E2%80%94retro%20slr%20camera%20clip%20art-6047203-432x432.png","xWH0xpSHtFcJoqbkqCUR0w==":"image-removebg-preview-432x432.png","kE/7gp4TRU7HIAB2xqZtVQ==":"mbr-1181x787.jpg","3iV1/gRL5kwu0mHP5nLP/A==":"mbr-1181x782.jpg","pwl8D5VOLN0eaHB8Bzel1w==":"mbr-1181x1772.jpg","xPFgcmJF9LCHfSyW4KNFtw==":"mbr-1-1181x787.jpg","Jvo+WwTaNjsjS/3HH9WIZA==":"mbr-2-1181x787.jpg","NBq7Y8QEiajkkPPLcFBf0g==":"mbr-1181x731.jpg","vEhHypvv1PVFbakrau5XvQ==":"mbr-1181x790.jpg"}